chess_uci_mcp/__init__.py
chess_uci_mcp/__main__.py
chess_uci_mcp/engine.py
chess_uci_mcp/server.py
chess_uci_mcp-0.1.1.dist-info/licenses/LICENSE
chess_uci_mcp-0.1.1.dist-info/METADATA
chess_uci_mcp-0.1.1.dist-info/WHEEL
chess_uci_mcp-0.1.1.dist-info/entry_points.txt
chess_uci_mcp-0.1.1.dist-info/top_level.txt
chess_uci_mcp-0.1.1.dist-info/RECORD
